{
  "Name": "Baker's Basic Cake Mix",
  "Description": "The basis of many cake recipes.",
  "Category": "ArtisanGoods",
  "Edibility": 5,
  "Price": 489,
  "IsColored": false,
  "Recipe": null,
  "GiftTastes":
    {
		"Dislike": ["Abigail", "Alex", "Caroline", "Clint", "Demetrius", "Dwarf", "Elliott", "Emily", "Evelyn", "George", "Gus", "Haley", "Harvey", "Jas", "Jodi", "Kent", "Krobus", "Leah", "Lewis", "Linus", "Marnie", "Maru", "Pam", "Penny", "Pierre", "Robin", "Sam", "Sandy", "Sebastian", "Shane", "Vincent", "Willy", "Wizard"],
    },
  "NameLocalization":
    {
        "es": "", //Spansih
        "ko": "", //Korean
        "de": "", //German
        "fr": "", //French
        "hu": "", //Hungarian
        "it": "", //Italian
        "ja": "", //Japanese
        "pt": "", //Portuguese
        "ru": "", //Russian
        "tr": "", //Turkish
        "zh": "贝克的基础蛋糕混合物", //Chinese (Simplified)
    },
    "DescriptionLocalization":
    {
        "es": "", //Spansih
        "ko": "", //Korean
        "de": "", //German
        "fr": "", //French
        "hu": "", //Hungarian
        "it": "", //Italian
        "ja": "", //Japanese
        "pt": "", //Portuguese
        "ru": "", //Russian
        "tr": "", //Turkish
        "zh": "许多蛋糕食谱的基础。", //Chinese (Simplified)
    }
}