{
  "Name": "Spooky Jack-O-Lantern",
  "Description": "A spooky fall decoration!",
  "Price": 300,
  "ProvidesLight": false,
  "Recipe":
    {
        "ResultCount": 1,
        "Ingredients": [
        {
            "Object": "Futsu Pumpkin",
            "Count": 1,
        }],
        //"IsDefault": true,
    },
    "GiftTastes":
    {
        "Love": ["Abigail", "Dwarf", "Krobus", "Wizard"],
        "Like": ["Alex", "Caroline", "Clint", "Demetrius", "Elliott", "Evelyn", "George", "Gus", "Jodi", "Kent", "Leah", "Linus", "Marnie", "Maru", "Penny", "Pierre", "Robin", "Sandy", "Shane", "Willy"],
        "Dislike": ["Harvey", "Haley", "Sebastian", "Emily", "Pam"],
        "Hate": ["Lewis", "Sam", "Vincent", "Jas"]
    },
    "NameLocalization":
    {
        //"es": "",
        //"ko": "",
        //"de": "",
        //"fr": "",
        //"hu": "",
        //"it": "",
        //"ja": "",
        //"pt": "",
        //"ru": "",
        //"tr": "",
        "zh": "趣奇杰克南瓜灯",
    },
    "DescriptionLocalization":
    {
        //"es": "",
        //"ko": "",
        //"de": "",
        //"fr": "",
        //"hu": "",
        //"it": "",
        //"ja": "",
        //"pt": "",
        //"ru": "",
        //"tr": "",
        "zh": "一个趣奇味的秋日装饰！",
    }
}