[
	// Art Supply Maker
	{
		"ProducerName": "Art Supply Maker",
		"InputIdentifier": "Beeswax",
		"InputStack": 1,
		"FuelIdentifier": 382,
        "FuelStack": 1,
		"MinutesUntilReady": 1,
		"OutputIdentifier":"Crayons",
		"InputPriceBased": false,
		"OutputPriceIncrement": 225,
		"OutputPriceMultiplier": 1,
		"KeepInputQuanlity": true,
		"OutputQuality": 0,
		"OutputStack": 1,
		"Sounds": ["Ship"],
        "PlacingAnimation": null,
        "PlacingAnimationColorName": "White",
	},
	{
		"ProducerName": "Art Supply Maker",
		"InputIdentifier": 330,
		"InputStack": 1,
		"FuelIdentifier": 382,
        "FuelStack": 1,
		"MinutesUntilReady": 2000,
		"OutputIdentifier":"Magic Clay",
		"InputPriceBased": false,
		"OutputPriceIncrement": 225,
		"OutputPriceMultiplier": 1,
		"KeepInputQuanlity": true,
		"OutputQuality": 0,
		"OutputStack": 1,
		"Sounds": ["Ship"],
        "PlacingAnimation": null,
        "PlacingAnimationColorName": "White",
	},
	{
		"ProducerName": "Art Supply Maker",
		"InputIdentifier": 766,
		"InputStack": 1,
		"FuelIdentifier": 382,
        "FuelStack": 1,
		"MinutesUntilReady": 2000,
		"OutputIdentifier":"Magic Marker",
		"InputPriceBased": false,
		"OutputPriceIncrement": 225,
		"OutputPriceMultiplier": 1,
		"KeepInputQuanlity": true,
		"OutputQuality": 0,
		"OutputStack": 1,
		"Sounds": ["Ship"],
        "PlacingAnimation": null,
        "PlacingAnimationColorName": "White",
	},
	{
		"ProducerName": "Art Supply Maker",
		"InputIdentifier": 247,
		"InputStack": 1,
		"FuelIdentifier": 382,
        "FuelStack": 1,
		"MinutesUntilReady": 2000,
		"OutputIdentifier":"Magic Paint",
		"InputPriceBased": false,
		"OutputPriceIncrement": 225,
		"OutputPriceMultiplier": 1,
		"KeepInputQuanlity": true,
		"OutputQuality": 0,
		"OutputStack": 1,
		"Sounds": ["Ship"],
        "PlacingAnimation": null,
        "PlacingAnimationColorName": "White",
	},
	{
		"ProducerName": "Art Supply Maker",
		"InputIdentifier": 393,
		"InputStack": 1,
		"FuelIdentifier": 382,
        "FuelStack": 1,
		"MinutesUntilReady": 2000,
		"OutputIdentifier":"Watercolors",
		"InputPriceBased": false,
		"OutputPriceIncrement": 225,
		"OutputPriceMultiplier": 1,
		"KeepInputQuanlity": true,
		"OutputQuality": 0,
		"OutputStack": 1,
		"Sounds": ["Ship"],
        "PlacingAnimation": null,
        "PlacingAnimationColorName": "White",
	},
	{
		"ProducerName": "Art Supply Maker",
		"InputIdentifier": 388,
		"InputStack": 1,
		"FuelIdentifier": 771,
        "FuelStack": 1,
		"MinutesUntilReady": 2000,
		"OutputIdentifier":"Paint Brush",
		"InputPriceBased": false,
		"OutputPriceIncrement": 225,
		"OutputPriceMultiplier": 1,
		"KeepInputQuanlity": true,
		"OutputQuality": 0,
		"OutputStack": 1,
		"Sounds": ["Ship"],
        "PlacingAnimation": null,
        "PlacingAnimationColorName": "White",
	},
	// Cosmetics Maker
	{
		"ProducerName": "Cosmetics Maker",
		"InputIdentifier": 394,
		"InputStack": 1,
		"FuelIdentifier": 330,
        "FuelStack": 1,
		"MinutesUntilReady": 2000,
		"OutputIdentifier":"Palette",
		"InputPriceBased": false,
		"OutputPriceIncrement": 225,
		"OutputPriceMultiplier": 1,
		"KeepInputQuanlity": true,
		"OutputQuality": 0,
		"OutputStack": 1,
		"Sounds": ["Ship"],
        "PlacingAnimation": null,
        "PlacingAnimationColorName": "White",
	},
	{
		"ProducerName": "Cosmetics Maker",
		"InputIdentifier": 393,
		"InputStack": 1,
		"FuelIdentifier": 330,
        "FuelStack": 1,
		"MinutesUntilReady": 2000,
		"OutputIdentifier":"Blush",
		"InputPriceBased": false,
		"OutputPriceIncrement": 225,
		"OutputPriceMultiplier": 1,
		"KeepInputQuanlity": true,
		"OutputQuality": 0,
		"OutputStack": 1,
		"Sounds": ["Ship"],
        "PlacingAnimation": null,
        "PlacingAnimationColorName": "White",
	},
	{
		"ProducerName": "Cosmetics Maker",
		"InputIdentifier": 82,
		"InputStack": 1,
		"FuelIdentifier": 330,
        "FuelStack": 1,
		"MinutesUntilReady": 2000,
		"OutputIdentifier":"Lipstick",
		"InputPriceBased": false,
		"OutputPriceIncrement": 225,
		"OutputPriceMultiplier": 1,
		"KeepInputQuanlity": true,
		"OutputQuality": 0,
		"OutputStack": 1,
		"Sounds": ["Ship"],
        "PlacingAnimation": null,
        "PlacingAnimationColorName": "White",
	},
	{
		"ProducerName": "Cosmetics Maker",
		"InputIdentifier": 382,
		"InputStack": 1,
		"FuelIdentifier": 330,
        "FuelStack": 1,
		"MinutesUntilReady": 2000,
		"OutputIdentifier":"Mascara",
		"InputPriceBased": false,
		"OutputPriceIncrement": 225,
		"OutputPriceMultiplier": 1,
		"KeepInputQuanlity": true,
		"OutputQuality": 0,
		"OutputStack": 1,
		"Sounds": ["Ship"],
        "PlacingAnimation": null,
        "PlacingAnimationColorName": "White",
	},
	{
		"ProducerName": "Cosmetics Maker",
		"InputIdentifier": 768,
		"InputStack": 1,
		"FuelIdentifier": 436,
        "FuelStack": 1,
		"MinutesUntilReady": 2000,
		"OutputIdentifier":"Sunscreen",
		"InputPriceBased": false,
		"OutputPriceIncrement": 225,
		"OutputPriceMultiplier": 1,
		"KeepInputQuanlity": true,
		"OutputQuality": 0,
		"OutputStack": 1,
		"Sounds": ["Ship"],
        "PlacingAnimation": null,
        "PlacingAnimationColorName": "White",
	},
	{
		"ProducerName": "Cosmetics Maker",
		"InputIdentifier": 769,
		"InputStack": 1,
		"FuelIdentifier": 436,
        "FuelStack": 1,
		"MinutesUntilReady": 2000,
		"OutputIdentifier":"Night Cream",
		"InputPriceBased": false,
		"OutputPriceIncrement": 225,
		"OutputPriceMultiplier": 1,
		"KeepInputQuanlity": true,
		"OutputQuality": 0,
		"OutputStack": 1,
		"Sounds": ["Ship"],
        "PlacingAnimation": null,
        "PlacingAnimationColorName": "White",
	},
	{
		"ProducerName": "Cosmetics Maker",
		"InputIdentifier": 88,
		"InputStack": 1,
		"FuelIdentifier": 436,
        "FuelStack": 1,
		"MinutesUntilReady": 2000,
		"OutputIdentifier":"Lotion",
		"InputPriceBased": false,
		"OutputPriceIncrement": 225,
		"OutputPriceMultiplier": 1,
		"KeepInputQuanlity": true,
		"OutputQuality": 0,
		"OutputStack": 1,
		"Sounds": ["Ship"],
        "PlacingAnimation": null,
        "PlacingAnimationColorName": "White",
	},
	// Dye Maker
	{
		"ProducerName": "Dye Maker",
		"InputIdentifier": 18,
		"InputStack": 1,
		"FuelIdentifier": 247,
        "FuelStack": 1,
		"MinutesUntilReady": 1000,
		"OutputIdentifier":"Yellow Dye",
		"InputPriceBased": false,
		"OutputPriceIncrement": 225,
		"OutputPriceMultiplier": 1,
		"KeepInputQuanlity": true,
		"OutputQuality": 0,
		"OutputStack": 1,
		"Sounds": ["Ship"],
        "PlacingAnimation": null,
        "PlacingAnimationColorName": "White",
	},
	{
		"ProducerName": "Dye Maker",
		"InputIdentifier": 396,
		"InputStack": 1,
		"FuelIdentifier": 247,
        "FuelStack": 1,
		"MinutesUntilReady": 1000,
		"OutputIdentifier":"Orange Dye",
		"InputPriceBased": false,
		"OutputPriceIncrement": 225,
		"OutputPriceMultiplier": 1,
		"KeepInputQuanlity": true,
		"OutputQuality": 0,
		"OutputStack": 1,
		"Sounds": ["Ship"],
        "PlacingAnimation": null,
        "PlacingAnimationColorName": "White",
	},
	{
		"ProducerName": "Dye Maker",
		"InputIdentifier": 402,
		"InputStack": 1,
		"FuelIdentifier": 247,
        "FuelStack": 1,
		"MinutesUntilReady": 1000,
		"OutputIdentifier":"Pink Dye",
		"InputPriceBased": false,
		"OutputPriceIncrement": 225,
		"OutputPriceMultiplier": 1,
		"KeepInputQuanlity": true,
		"OutputQuality": 0,
		"OutputStack": 1,
		"Sounds": ["Ship"],
        "PlacingAnimation": null,
        "PlacingAnimationColorName": "White",
	},
	{
		"ProducerName": "Dye Maker",
		"InputIdentifier": 296,
		"InputStack": 1,
		"FuelIdentifier": 247,
        "FuelStack": 1,
		"MinutesUntilReady": 1000,
		"OutputIdentifier":"Red Dye",
		"InputPriceBased": false,
		"OutputPriceIncrement": 225,
		"OutputPriceMultiplier": 1,
		"KeepInputQuanlity": true,
		"OutputQuality": 0,
		"OutputStack": 1,
		"Sounds": ["Ship"],
        "PlacingAnimation": null,
        "PlacingAnimationColorName": "White",
	},
	{
		"ProducerName": "Dye Maker",
		"InputIdentifier": 418,
		"InputStack": 1,
		"FuelIdentifier": 247,
        "FuelStack": 1,
		"MinutesUntilReady": 1000,
		"OutputIdentifier":"Purple Dye",
		"InputPriceBased": false,
		"OutputPriceIncrement": 225,
		"OutputPriceMultiplier": 1,
		"KeepInputQuanlity": true,
		"OutputQuality": 0,
		"OutputStack": 1,
		"Sounds": ["Ship"],
        "PlacingAnimation": null,
        "PlacingAnimationColorName": "White",
	},
	{
		"ProducerName": "Dye Maker",
		"InputIdentifier": 414,
		"InputStack": 1,
		"FuelIdentifier": 247,
        "FuelStack": 1,
		"MinutesUntilReady": 1000,
		"OutputIdentifier":"Blue Dye",
		"InputPriceBased": false,
		"OutputPriceIncrement": 225,
		"OutputPriceMultiplier": 1,
		"KeepInputQuanlity": true,
		"OutputQuality": 0,
		"OutputStack": 1,
		"Sounds": ["Ship"],
        "PlacingAnimation": null,
        "PlacingAnimationColorName": "White",
	},
	{
		"ProducerName": "Dye Maker",
		"InputIdentifier": 372,
		"InputStack": 1,
		"FuelIdentifier": 247,
        "FuelStack": 1,
		"MinutesUntilReady": 1000,
		"OutputIdentifier":"Turquoise Dye",
		"InputPriceBased": false,
		"OutputPriceIncrement": 225,
		"OutputPriceMultiplier": 1,
		"KeepInputQuanlity": true,
		"OutputQuality": 0,
		"OutputStack": 1,
		"Sounds": ["Ship"],
        "PlacingAnimation": null,
        "PlacingAnimationColorName": "White",
	},
	{
		"ProducerName": "Dye Maker",
		"InputIdentifier": 259,
		"InputStack": 1,
		"FuelIdentifier": 247,
        "FuelStack": 1,
		"MinutesUntilReady": 1000,
		"OutputIdentifier":"Green Dye",
		"InputPriceBased": false,
		"OutputPriceIncrement": 225,
		"OutputPriceMultiplier": 1,
		"KeepInputQuanlity": true,
		"OutputQuality": 0,
		"OutputStack": 1,
		"Sounds": ["Ship"],
        "PlacingAnimation": null,
        "PlacingAnimationColorName": "White",
	},
	{
		"ProducerName": "Dye Maker",
		"InputIdentifier": 382,
		"InputStack": 1,
		"FuelIdentifier": 247,
        "FuelStack": 1,
		"MinutesUntilReady": 1000,
		"OutputIdentifier":"Black Dye",
		"InputPriceBased": false,
		"OutputPriceIncrement": 225,
		"OutputPriceMultiplier": 1,
		"KeepInputQuanlity": true,
		"OutputQuality": 0,
		"OutputStack": 1,
		"Sounds": ["Ship"],
        "PlacingAnimation": null,
        "PlacingAnimationColorName": "White",
	},
	// Lollipop Maker
	{
		"ProducerName": "Lollipop Maker",
		"InputIdentifier": "Lemon",
		"InputStack": 1,
		"FuelIdentifier": 245,
        "FuelStack": 1,
		"MinutesUntilReady": 1000,
		"OutputIdentifier":"Lemon Lollipop",
		"InputPriceBased": false,
		"OutputPriceIncrement": 225,
		"OutputPriceMultiplier": 1,
		"KeepInputQuanlity": true,
		"OutputQuality": 0,
		"OutputStack": 1,
		"Sounds": ["Ship"],
        "PlacingAnimation": null,
        "PlacingAnimationColorName": "White",
	},
	{
		"ProducerName": "Lollipop Maker",
		"InputIdentifier": 635,
		"InputStack": 1,
		"FuelIdentifier": 245,
        "FuelStack": 1,
		"MinutesUntilReady": 1000,
		"OutputIdentifier":"Orange Lollipop",
		"InputPriceBased": false,
		"OutputPriceIncrement": 225,
		"OutputPriceMultiplier": 1,
		"KeepInputQuanlity": true,
		"OutputQuality": 0,
		"OutputStack": 1,
		"Sounds": ["Ship"],
        "PlacingAnimation": null,
        "PlacingAnimationColorName": "White",
	},
	{
		"ProducerName": "Lollipop Maker",
		"InputIdentifier": 400,
		"InputStack": 1,
		"FuelIdentifier": 245,
        "FuelStack": 1,
		"MinutesUntilReady": 1000,
		"OutputIdentifier":"Strawberry Lollipop",
		"InputPriceBased": false,
		"OutputPriceIncrement": 225,
		"OutputPriceMultiplier": 1,
		"KeepInputQuanlity": true,
		"OutputQuality": 0,
		"OutputStack": 1,
		"Sounds": ["Ship"],
        "PlacingAnimation": null,
        "PlacingAnimationColorName": "White",
	},
	{
		"ProducerName": "Lollipop Maker",
		"InputIdentifier": "Mint",
		"InputStack": 1,
		"FuelIdentifier": 245,
        "FuelStack": 1,
		"MinutesUntilReady": 1000,
		"OutputIdentifier":"Mint Lollipop",
		"InputPriceBased": false,
		"OutputPriceIncrement": 225,
		"OutputPriceMultiplier": 1,
		"KeepInputQuanlity": true,
		"OutputQuality": 0,
		"OutputStack": 1,
		"Sounds": ["Ship"],
        "PlacingAnimation": null,
        "PlacingAnimationColorName": "White",
	},
	{
		"ProducerName": "Lollipop Maker",
		"InputIdentifier": 268,
		"InputStack": 1,
		"FuelIdentifier": 245,
        "FuelStack": 1,
		"MinutesUntilReady": 1000,
		"OutputIdentifier":"Starfruit Lollipop",
		"InputPriceBased": false,
		"OutputPriceIncrement": 225,
		"OutputPriceMultiplier": 1,
		"KeepInputQuanlity": true,
		"OutputQuality": 0,
		"OutputStack": 1,
		"Sounds": ["Ship"],
        "PlacingAnimation": null,
        "PlacingAnimationColorName": "White",
	},
	{
		"ProducerName": "Lollipop Maker",
		"InputIdentifier": 74,
		"InputStack": 1,
		"FuelIdentifier": 245,
        "FuelStack": 1,
		"MinutesUntilReady": 1000,
		"OutputIdentifier":"Rainbow Lollipop",
		"InputPriceBased": false,
		"OutputPriceIncrement": 225,
		"OutputPriceMultiplier": 1,
		"KeepInputQuanlity": true,
		"OutputQuality": 0,
		"OutputStack": 1,
		"Sounds": ["Ship"],
        "PlacingAnimation": null,
        "PlacingAnimationColorName": "White",
	},
	{
		"ProducerName": "Lollipop Maker",
		"InputIdentifier": 258,
		"InputStack": 1,
		"FuelIdentifier": 245,
        "FuelStack": 1,
		"MinutesUntilReady": 1000,
		"OutputIdentifier":"Blueberry Lollipop",
		"InputPriceBased": false,
		"OutputPriceIncrement": 225,
		"OutputPriceMultiplier": 1,
		"KeepInputQuanlity": true,
		"OutputQuality": 0,
		"OutputStack": 1,
		"Sounds": ["Ship"],
        "PlacingAnimation": null,
        "PlacingAnimationColorName": "White",
	},
	{
		"ProducerName": "Lollipop Maker",
		"InputIdentifier": 398,
		"InputStack": 1,
		"FuelIdentifier": 245,
        "FuelStack": 1,
		"MinutesUntilReady": 1000,
		"OutputIdentifier":"Grape Lollipop",
		"InputPriceBased": false,
		"OutputPriceIncrement": 225,
		"OutputPriceMultiplier": 1,
		"KeepInputQuanlity": true,
		"OutputQuality": 0,
		"OutputStack": 1,
		"Sounds": ["Ship"],
        "PlacingAnimation": null,
        "PlacingAnimationColorName": "White",
	},
	{
		"ProducerName": "Lollipop Maker",
		"InputIdentifier": 167,
		"InputStack": 1,
		"FuelIdentifier": 245,
        "FuelStack": 1,
		"MinutesUntilReady": 1000,
		"OutputIdentifier":"Cola Lollipop",
		"InputPriceBased": false,
		"OutputPriceIncrement": 225,
		"OutputPriceMultiplier": 1,
		"KeepInputQuanlity": true,
		"OutputQuality": 0,
		"OutputStack": 1,
		"Sounds": ["Ship"],
        "PlacingAnimation": null,
        "PlacingAnimationColorName": "White",
	},
	// Macaron Oven
	{
		"ProducerName": "Macaron Oven",
		"InputIdentifier": 636,
		"InputStack": 1,
		"FuelIdentifier": 245,
        "FuelStack": 1,
		"MinutesUntilReady": 1000,
		"OutputIdentifier":"Peach Macaron",
		"InputPriceBased": false,
		"OutputPriceIncrement": 225,
		"OutputPriceMultiplier": 1,
		"KeepInputQuanlity": true,
		"OutputQuality": 0,
		"OutputStack": 1,
		"Sounds": ["Furnace"],
        "PlacingAnimation": null,
        "PlacingAnimationColorName": "White",
	},
	{
		"ProducerName": "Macaron Oven",
		"InputIdentifier": 454,
		"InputStack": 1,
		"FuelIdentifier": 245,
        "FuelStack": 1,
		"MinutesUntilReady": 1000,
		"OutputIdentifier":"Ancient Macaron",
		"InputPriceBased": false,
		"OutputPriceIncrement": 225,
		"OutputPriceMultiplier": 1,
		"KeepInputQuanlity": true,
		"OutputQuality": 0,
		"OutputStack": 1,
		"Sounds": ["Furnace"],
        "PlacingAnimation": null,
        "PlacingAnimationColorName": "White",
	},
	{
		"ProducerName": "Macaron Oven",
		"InputIdentifier": "Lemon",
		"InputStack": 1,
		"FuelIdentifier": 245,
        "FuelStack": 1,
		"MinutesUntilReady": 1000,
		"OutputIdentifier":"Lemon Macaron",
		"InputPriceBased": false,
		"OutputPriceIncrement": 225,
		"OutputPriceMultiplier": 1,
		"KeepInputQuanlity": true,
		"OutputQuality": 0,
		"OutputStack": 1,
		"Sounds": ["Furnace"],
        "PlacingAnimation": null,
        "PlacingAnimationColorName": "White",
	},
	{
		"ProducerName": "Macaron Oven",
		"InputIdentifier": 635,
		"InputStack": 1,
		"FuelIdentifier": 245,
        "FuelStack": 1,
		"MinutesUntilReady": 1000,
		"OutputIdentifier":"Orange Macaron",
		"InputPriceBased": false,
		"OutputPriceIncrement": 225,
		"OutputPriceMultiplier": 1,
		"KeepInputQuanlity": true,
		"OutputQuality": 0,
		"OutputStack": 1,
		"Sounds": ["Furnace"],
        "PlacingAnimation": null,
        "PlacingAnimationColorName": "White",
	},
	{
		"ProducerName": "Macaron Oven",
		"InputIdentifier": 595,
		"InputStack": 1,
		"FuelIdentifier": 245,
        "FuelStack": 1,
		"MinutesUntilReady": 1000,
		"OutputIdentifier":"Fairy Macaron",
		"InputPriceBased": false,
		"OutputPriceIncrement": 225,
		"OutputPriceMultiplier": 1,
		"KeepInputQuanlity": true,
		"OutputQuality": 0,
		"OutputStack": 1,
		"Sounds": ["Furnace"],
        "PlacingAnimation": null,
        "PlacingAnimationColorName": "White",
	},
	{
		"ProducerName": "Macaron Oven",
		"InputIdentifier": "Shaded Violet",
		"InputStack": 1,
		"FuelIdentifier": 245,
        "FuelStack": 1,
		"MinutesUntilReady": 1000,
		"OutputIdentifier":"Violet Macaron",
		"InputPriceBased": false,
		"OutputPriceIncrement": 225,
		"OutputPriceMultiplier": 1,
		"KeepInputQuanlity": true,
		"OutputQuality": 0,
		"OutputStack": 1,
		"Sounds": ["Furnace"],
        "PlacingAnimation": null,
        "PlacingAnimationColorName": "White",
	},
	{
		"ProducerName": "Macaron Oven",
		"InputIdentifier": "Mint",
		"InputStack": 1,
		"FuelIdentifier": 245,
        "FuelStack": 1,
		"MinutesUntilReady": 1000,
		"OutputIdentifier":"Mint Macaron",
		"InputPriceBased": false,
		"OutputPriceIncrement": 225,
		"OutputPriceMultiplier": 1,
		"KeepInputQuanlity": true,
		"OutputQuality": 0,
		"OutputStack": 1,
		"Sounds": ["Furnace"],
        "PlacingAnimation": null,
        "PlacingAnimationColorName": "White",
	},
	{
		"ProducerName": "Macaron Oven",
		"InputIdentifier": "Raspberry",
		"InputStack": 1,
		"FuelIdentifier": "Chocolate",
        "FuelStack": 1,
		"AdditionalFuel":
        {
            "245": 1,
        },
		"MinutesUntilReady": 1000,
		"OutputIdentifier":"Chocoberry Macaron",
		"InputPriceBased": false,
		"OutputPriceIncrement": 225,
		"OutputPriceMultiplier": 1,
		"KeepInputQuanlity": true,
		"OutputQuality": 0,
		"OutputStack": 1,
		"Sounds": ["Furnace"],
        "PlacingAnimation": null,
        "PlacingAnimationColorName": "White",
	},
	{
		"ProducerName": "Macaron Oven",
		"InputIdentifier": 395,
		"InputStack": 1,
		"FuelIdentifier": "Chocolate",
        "FuelStack": 1,
		"AdditionalFuel":
        {
            "245": 1,
        },
		"MinutesUntilReady": 1000,
		"OutputIdentifier":"Chocoffee Macaron",
		"InputPriceBased": false,
		"OutputPriceIncrement": 225,
		"OutputPriceMultiplier": 1,
		"KeepInputQuanlity": true,
		"OutputQuality": 0,
		"OutputStack": 1,
		"Sounds": ["Furnace"],
        "PlacingAnimation": null,
        "PlacingAnimationColorName": "White",
	},
	{
		"ProducerName": "Macaron Oven",
		"InputIdentifier": 400,
		"InputStack": 1,
		"FuelIdentifier": "Vanilla",
        "FuelStack": 1,
		"AdditionalFuel":
        {
            "245": 1,
        },
		"MinutesUntilReady": 1000,
		"OutputIdentifier":"Vaniberry Macaron",
		"InputPriceBased": false,
		"OutputPriceIncrement": 225,
		"OutputPriceMultiplier": 1,
		"KeepInputQuanlity": true,
		"OutputQuality": 0,
		"OutputStack": 1,
		"Sounds": ["Furnace"],
        "PlacingAnimation": null,
        "PlacingAnimationColorName": "White",
	},
	// Nail Polish Maker
	{
		"ProducerName": "Nail Polish Maker",
		"InputIdentifier": 558,
		"InputStack": 1,
		"FuelIdentifier": 86,
        "FuelStack": 1,
		"MinutesUntilReady": 1000,
		"OutputIdentifier":"Sunset Polish",
		"InputPriceBased": false,
		"OutputPriceIncrement": 225,
		"OutputPriceMultiplier": 1,
		"KeepInputQuanlity": true,
		"OutputQuality": 0,
		"OutputStack": 1,
		"Sounds": ["Furnace"],
        "PlacingAnimation": null,
        "PlacingAnimationColorName": "White",
	},
	{
		"ProducerName": "Nail Polish Maker",
		"InputIdentifier": 84,
		"InputStack": 1,
		"FuelIdentifier": 86,
        "FuelStack": 1,
		"MinutesUntilReady": 1000,
		"OutputIdentifier":"Frozen Polish",
		"InputPriceBased": false,
		"OutputPriceIncrement": 225,
		"OutputPriceMultiplier": 1,
		"KeepInputQuanlity": true,
		"OutputQuality": 0,
		"OutputStack": 1,
		"Sounds": ["Furnace"],
        "PlacingAnimation": null,
        "PlacingAnimationColorName": "White",
	},
	{
		"ProducerName": "Nail Polish Maker",
		"InputIdentifier": 578,
		"InputStack": 1,
		"FuelIdentifier": 86,
        "FuelStack": 1,
		"MinutesUntilReady": 1000,
		"OutputIdentifier":"Candy Polish",
		"InputPriceBased": false,
		"OutputPriceIncrement": 225,
		"OutputPriceMultiplier": 1,
		"KeepInputQuanlity": true,
		"OutputQuality": 0,
		"OutputStack": 1,
		"Sounds": ["Furnace"],
        "PlacingAnimation": null,
        "PlacingAnimationColorName": "White",
	},
	{
		"ProducerName": "Nail Polish Maker",
		"InputIdentifier": 564,
		"InputStack": 1,
		"FuelIdentifier": 86,
        "FuelStack": 1,
		"MinutesUntilReady": 1000,
		"OutputIdentifier":"Holographic Polish",
		"InputPriceBased": false,
		"OutputPriceIncrement": 225,
		"OutputPriceMultiplier": 1,
		"KeepInputQuanlity": true,
		"OutputQuality": 0,
		"OutputStack": 1,
		"Sounds": ["Furnace"],
        "PlacingAnimation": null,
        "PlacingAnimationColorName": "White",
	},
	{
		"ProducerName": "Nail Polish Maker",
		"InputIdentifier": 394,
		"InputStack": 1,
		"FuelIdentifier": 86,
        "FuelStack": 1,
		"MinutesUntilReady": 1000,
		"OutputIdentifier":"Lagoon Polish",
		"InputPriceBased": false,
		"OutputPriceIncrement": 225,
		"OutputPriceMultiplier": 1,
		"KeepInputQuanlity": true,
		"OutputQuality": 0,
		"OutputStack": 1,
		"Sounds": ["Furnace"],
        "PlacingAnimation": null,
        "PlacingAnimationColorName": "White",
	},
	{
		"ProducerName": "Nail Polish Maker",
		"InputIdentifier": 444,
		"InputStack": 1,
		"FuelIdentifier": 86,
        "FuelStack": 1,
		"MinutesUntilReady": 1000,
		"OutputIdentifier":"Magic Polish",
		"InputPriceBased": false,
		"OutputPriceIncrement": 225,
		"OutputPriceMultiplier": 1,
		"KeepInputQuanlity": true,
		"OutputQuality": 0,
		"OutputStack": 1,
		"Sounds": ["Furnace"],
        "PlacingAnimation": null,
        "PlacingAnimationColorName": "White",
	},
	{
		"ProducerName": "Nail Polish Maker",
		"InputIdentifier": 561,
		"InputStack": 1,
		"FuelIdentifier": 86,
        "FuelStack": 1,
		"MinutesUntilReady": 1000,
		"OutputIdentifier":"Midnight Polish",
		"InputPriceBased": false,
		"OutputPriceIncrement": 225,
		"OutputPriceMultiplier": 1,
		"KeepInputQuanlity": true,
		"OutputQuality": 0,
		"OutputStack": 1,
		"Sounds": ["Furnace"],
        "PlacingAnimation": null,
        "PlacingAnimationColorName": "White",
	},
	{
		"ProducerName": "Nail Polish Maker",
		"InputIdentifier": 393,
		"InputStack": 1,
		"FuelIdentifier": 86,
        "FuelStack": 1,
		"MinutesUntilReady": 1000,
		"OutputIdentifier":"Glamour Polish",
		"InputPriceBased": false,
		"OutputPriceIncrement": 225,
		"OutputPriceMultiplier": 1,
		"KeepInputQuanlity": true,
		"OutputQuality": 0,
		"OutputStack": 1,
		"Sounds": ["Furnace"],
        "PlacingAnimation": null,
        "PlacingAnimationColorName": "White",
	},
	]