{
    "Name": "Black Boy Peach",
    "Description": "A rare hardy heritage peach that has a wonderful rich flavor!",
    "Category": "Fruit",
    "Edibility": 20,
    "Price": 250,
    "IsColored": false,
    "Recipe": null,
    "GiftTastes":
    {
        "Love": ["Abigail", "Dwarf", "Krobus", "Wizard"],
        "Like": ["Alex", "Caroline", "Clint", "Demetrius", "Elliott", "Evelyn", "George", "Gus", "Jodi", "Kent", "Leah", "Linus", "Marnie", "Maru", "Penny", "Pierre", "Robin", "Sandy", "Shane", "Willy"],
        "Dislike": ["Harvey", "Haley", "Sebastian", "Emily", "Pam"],
        "Hate": ["Lewis", "Sam", "Vincent", "Jas"]
    },
    "NameLocalization":
    {
        //"es": "",
        //"ko": "",
        //"de": "",
        //"fr": "",
        //"hu": "",
        //"it": "",
        //"ja": "",
        //"pt": "",
        //"ru": "",
        //"tr": "",
        "zh": "黑人男孩桃子",
    },
    "DescriptionLocalization":
    {
        //"es": "",
        //"ko": "",
        //"de": "",
        //"fr": "",
        //"hu": "",
        //"it": "",
        //"ja": "",
        //"pt": "",
        //"ru": "",
        //"tr": "",
        "zh": "一个罕见的自适应力强的桃子，有着美妙而丰富的味道！",
    }
}